tisanecodegenerator/__init__.py
tisanecodegenerator/codeGenerator.py
tisanecodegenerator/codeGeneratorStrings.py
tisanecodegenerator/statisticalModel.py
tisanecodegenerator/strings.json
tisanecodegenerator-0.1.2.dist-info/WHEEL
tisanecodegenerator-0.1.2.dist-info/METADATA
tisanecodegenerator-0.1.2.dist-info/RECORD
