Metadata-Version: 2.1
Name: tisanecodegenerator
Version: 0.1.2
Summary: Code generator for Tisane
Author: Eunice Jun
Author-email: eunice.m.jun@gmail.com
Requires-Python: >=3.8,<4.0
Classifier: Programming Language :: Python :: 3
Classifier: Programming Language :: Python :: 3.8
Classifier: Programming Language :: Python :: 3.9
Requires-Dist: pandas (>=1.5.0,<2.0.0)
